dfrobot_mcp/__init__.py
dfrobot_mcp-0.1.0.dist-info/METADATA
dfrobot_mcp-0.1.0.dist-info/WHEEL
dfrobot_mcp-0.1.0.dist-info/entry_points.txt
dfrobot_mcp-0.1.0.dist-info/RECORD
