Metadata-Version: 2.4
Name: dfrobot-mcp
Version: 0.1.0
Summary: Add your description here
Author-email: falconxu <falcon.x@163.com>
Requires-Python: >=3.10
Requires-Dist: mcp[cli]>=1.10.1
